timetappy/__init__.py
timetappy/appointments.py
timetappy/auth.py
timetappy/calendar.py
timetappy/client.py
timetappy/clients.py
timetappy/locations.py
timetappy/services.py
timetappy/staff.py
timetappy/utils.py
timetappy-0.0.2a0.dist-info/LICENSE
timetappy-0.0.2a0.dist-info/METADATA
timetappy-0.0.2a0.dist-info/WHEEL
timetappy-0.0.2a0.dist-info/top_level.txt
timetappy-0.0.2a0.dist-info/RECORD
