Metadata-Version: 2.1
Name: timetappy
Version: 0.0.2a0
Summary: Unofficial API client wrapper around the TimeTap API
Home-page: https://github.com/ak9999/timetappy
Author: Abdullah 'AJ' Khan
Author-email: aj@ajkhan.me
License: UNKNOWN
Platform: UNKNOWN
Classifier: Programming Language :: Python :: 3
Classifier: Operating System :: OS Independent
Requires-Python: >=3.6
Requires-Dist: requests (>=2.23.0)
